odoo/addons/website_sale_product_model_viewer/README.rst
odoo/addons/website_sale_product_model_viewer/__init__.py
odoo/addons/website_sale_product_model_viewer/__manifest__.py
odoo/addons/website_sale_product_model_viewer/i18n/ca.po
odoo/addons/website_sale_product_model_viewer/i18n/es.po
odoo/addons/website_sale_product_model_viewer/i18n/fr.po
odoo/addons/website_sale_product_model_viewer/i18n/website_sale_product_model_viewer.pot
odoo/addons/website_sale_product_model_viewer/readme/CONTRIBUTORS.rst
odoo/addons/website_sale_product_model_viewer/readme/DESCRIPTION.rst
odoo/addons/website_sale_product_model_viewer/readme/ROADMAP.rst
odoo/addons/website_sale_product_model_viewer/readme/USAGE.rst
odoo/addons/website_sale_product_model_viewer/static/description/icon.png
odoo/addons/website_sale_product_model_viewer/static/description/index.html
odoo/addons/website_sale_product_model_viewer/static/src/js/product_model_viewer.js
odoo/addons/website_sale_product_model_viewer/views/frontend_templates.xml
odoo12_addon_website_sale_product_model_viewer-12.0.1.0.0.99.dev11.dist-info/METADATA
odoo12_addon_website_sale_product_model_viewer-12.0.1.0.0.99.dev11.dist-info/WHEEL
odoo12_addon_website_sale_product_model_viewer-12.0.1.0.0.99.dev11.dist-info/top_level.txt
odoo12_addon_website_sale_product_model_viewer-12.0.1.0.0.99.dev11.dist-info/RECORD
